nova/__init__.py
nova/common/__init__.py
nova/common/events.py
nova/common/job.py
nova/common/signals.py
nova_common-0.3.0.dist-info/LICENSE
nova_common-0.3.0.dist-info/METADATA
nova_common-0.3.0.dist-info/WHEEL
nova_common-0.3.0.dist-info/RECORD
